chip/__init__.py
chip/import_hook.py
chip/hd/__init__.py
chip/hd/hardware.py
chip/hd/utils.py
pyhd/__init__.py
pyhd/import_hook.py
pyhd/hd/__init__.py
pyhd/hd/hardware.py
pyhd/hd/utils.py
pyhdls/__init__.py
pyhdls/import_hook.py
pyhdls/hd/__init__.py
pyhdls/hd/hardware.py
pyhdls/hd/utils.py
pyhdls-0.0.1.dist-info/LICENSE
pyhdls-0.0.1.dist-info/METADATA
pyhdls-0.0.1.dist-info/WHEEL
pyhdls-0.0.1.dist-info/top_level.txt
pyhdls-0.0.1.dist-info/RECORD
