Metadata-Version: 2.1
Name: pyhdls
Version: 0.0.1
Summary: a python like hdl
Home-page: UNKNOWN
Author: jintao
Author-email: jintaos2@zju.edu.cn
License: UNKNOWN
Platform: UNKNOWN
Classifier: Development Status :: 1 - Planning
Classifier: Programming Language :: Python :: 3.10
Classifier: License :: OSI Approved :: MIT License
Classifier: Operating System :: OS Independent
Requires-Python: >=3.10
License-File: LICENSE
